crctools/__init__.py
crctools/__main__.py
crctools/py.typed
crctools/utils.py
crctools_DavidRodriguezSoaresCUI-0.0.4.dist-info/LICENSE
crctools_DavidRodriguezSoaresCUI-0.0.4.dist-info/METADATA
crctools_DavidRodriguezSoaresCUI-0.0.4.dist-info/WHEEL
crctools_DavidRodriguezSoaresCUI-0.0.4.dist-info/top_level.txt
crctools_DavidRodriguezSoaresCUI-0.0.4.dist-info/RECORD
