Metadata-Version: 2.1
Name: crctools-DavidRodriguezSoaresCUI
Version: 0.0.4
Summary: A simple tool to check file integrity using CRC32 hash in filename
Author-email: DavidRodriguezSoaresCUI <fireblaze904+crctools@gmail.com>
License: MIT License
Project-URL: Homepage, https://github.com/DavidRodriguezSoaresCUI/crctools
Project-URL: Bug Tracker, https://github.com/DavidRodriguezSoaresCUI/crctools/issues
Classifier: Programming Language :: Python :: 3
Classifier: License :: OSI Approved :: MIT License
Requires-Python: >=3.10
License-File: LICENSE
